Workbook

Sheet ⚠️ READ FIRST
A1: Q1 2026 RESEARCH PROJECT - MASTER WORKBOOK
A3: ALL DELIVERABLES DUE: EOD FRIDAY, DECEMBER 27, 2025
A5: 7 NON-NEGOTIABLE RULES
A6: Rule 1: | B6: Every claim needs a source. If you can't cite it, don't include it.
A7: Rule 2: | B7: Time boxes are hard limits. When you hit the limit, STOP and report status.
A8: Rule 3: | B8: No guessing on eligibility. Flag as 'UNCERTAIN - CEO REVIEW' and move on.
A9: Rule 4: | B9: No account creation or form submission. You prepare artifacts. I execute.
A10: Rule 5: | B10: No access to sensitive data. If a task seems to need it, escalate immediately.
A11: Rule 6: | B11: Quote exact language from sources. Don't paraphrase requirements.
A12: Rule 7: | B12: Document what you can't find. Gaps in information ARE information.
A14: ESCALATION TRIGGERS - Message Slack IMMEDIATELY if:
A15: • Time box exceeded and task isn't done
A16: • You need information that isn't publicly available
A17: • Eligibility language is ambiguous
A18: • You encounter a strategic decision point
A19: • Something suggests we might be misrepresenting ourselves
A21: DAILY CHECK-IN SCHEDULE
A22: Day | B22: Deadline | C22: Milestone
A23: Mon Dec 23 | B23: 6:00 PM | C23: Task 0: Source Document Library complete?
A24: Tue Dec 24 | B24: 3:00 PM | C24: Tasks 1A-1D: Analysis deliverables complete?
A25: Wed Dec 25 | B25: — | C25: Christmas (off)
A26: Thu Dec 26 | B26: 6:00 PM | C26: Tasks 2A-2D: Tools and applications drafted?
A27: Fri Dec 27 | B27: 5:00 PM | C27: FINAL: All deliverables submitted
A29: CHECK-IN FORMAT (Slack message):
A30: 1. COMPLETED: Task IDs and brief status
A31: 2. BLOCKED: What you couldn't complete and why
A32: 3. TOMORROW: What you'll work on next
A33: 4. QUESTIONS: Anything you need clarification on
A35: KEY BOOKMARKS
A36: Source | B36: URL / Path
A37: Federal Legislation | B37: govinfo.gov → Public Laws → P.L. 119-21
A38: IRS Guidance | B38: irs.gov → Publications 560, 969, 587, 463, 946
A39: AWS Activate | B39: aws.amazon.com/activate
A40: Google for Startups | B40: cloud.google.com/startup
A41: Microsoft Founders Hub | B41: foundershub.startups.microsoft.com
A42: Arizona Tax Credits | B42: azdor.gov
A43: Arizona Grants | B43: azcommerce.com

Sheet 📅 Tasks & Timeline
A1: TASK TRACKER
A3: Task ID | B3: Deliverable | C3: Tier | D3: Time Budget | E3: Due Date | F3: Status | G3: % Complete | H3: Notes
A4: 0 | B4: Source Document Library + Index | C4: T2 | D4: 3 hrs | E4: Mon Dec 23 | H4: Foundation - do this first
A5: 1A | B5: OBBBA Lever Library | C5: T2 | D5: 2 hrs | E5: Tue Dec 24 | H5: §174A, §179, §168k, §1202
A6: 1B | B6: Arizona Credit Checklist | C6: T1 | D6: 1 hr | E6: Tue Dec 24 | H6: Forms 321, 322, 323, 352
A7: 1C | B7: Pre-Flight Verification | C7: T1 | D7: 2 hrs | E7: Tue Dec 24 | H7: 6 applications × 6 questions
A8: 1D | B8: Program Fact Sheets | C8: T1 | D8: 1 hr | E8: Tue Dec 24 | H8: AWS, Google, Microsoft
A9: 2A | B9: Tax Calculator Workbook | C9: T2 | D9: 3 hrs | E9: Thu Dec 26 | H9: 7 worksheets with formulas
A10: 2B | B10: CEO Data Collection Checklist | C10: T0 | D10: 30 min | E10: Thu Dec 26 | H10: What Ryan needs to provide
A11: 2C | B11: Blind Application Packets | C11: T2 | D11: 2 hrs | E11: Thu Dec 26 | H11: 6 Word docs ready to submit
A12: 2D | B12: Program Proof Sheets | C12: T1 | D12: 1 hr | E12: Thu Dec 26 | H12: 15 fields × 2 companies
A13: 2E | B13: Vendor Whitelist + R&D Keywords | C13: T1 | D13: 1 hr | E13: Fri Dec 27 | H13: 25 vendors + 50 keywords
A14: 2F | B14: Grant Kill List | C14: T2 | D14: 2 hrs | E14: Fri Dec 27 | H14: Systematic elimination
A15: QA | B15: Review All Deliverables | C15: — | D15: 1 hr | E15: Fri Dec 27 | H15: Final quality check
... A17: 3B | B17: SBIR/STTR Viability | C17: T3 | D17: 2 hrs | E17: Fri Jan 10 | H17: POST-HOLIDAY: CEO review required
A20: TIER DEFINITIONS
A21: Tier | B21: Time | C21: Description | D21: Escalation Rule
A22: T0 | B22: 15-30 min | C22: Simple lookup, binary yes/no | D22: If >30 min, STOP and escalate
A23: T1 | B23: 1-2 hrs | C23: Structured form from known sources | D23: If >2 hrs, STOP and escalate
A24: T2 | B24: 2-4 hrs | C24: Research synthesis, multiple sources | D24: If >4 hrs, STOP and escalate
A25: T3 | B25: 4-8 hrs | C25: Strategic analysis, CEO review required | D25: Flag as CEO DECISION REQUIRED

Sheet 📁 Source Doc Index
A1: SOURCE DOCUMENT INDEX (Task 0F)
A2: Catalog every document you download. This is how I navigate the library.
A4: Filename | B4: Category | C4: Doc Type | D4: Source URL | E4: Date Downloaded | F4: Description | G4: Verified Auth? | H4: Notes
A5: 2025-07-04_GovInfo_PublicLaw_PL119-21_OBBBA.pdf | B5: Federal_Legislation | C5: Public Law | D5: govinfo.gov | F5: One Big Beautiful Bill Act | H5: Verify digital signature
B6: IRS_Guidance | C6: Publication | D6: irs.gov | F6: Publication 560 - SEP-IRA
B7: IRS_Guidance | C7: Publication | D7: irs.gov | F7: Publication 969 - HSA
B8: IRS_Guidance | C8: Publication | D8: irs.gov | F8: Publication 587 - Home Office
B9: IRS_Guidance | C9: Publication | D9: irs.gov | F9: Publication 463 - Vehicle/Travel
B10: IRS_Guidance | C10: Publication | D10: irs.gov | F10: Publication 946 - Depreciation
B11: IRS_Guidance | C11: Form | D11: irs.gov | F11: Form 4562 + Instructions
B12: IRS_Guidance | C12: Form | D12: irs.gov | F12: Form 8995 + Instructions - QBI
B13: IRS_Guidance | C13: IRB_Bulletin | D13: irs.gov | F13: IRB 2025-38 / Rev Proc 2025-23
B14: Cloud_Programs | C14: Terms of Service | D14: aws.amazon.com/activate | F14: AWS Activate Terms
B15: Cloud_Programs | C15: Eligibility | D15: aws.amazon.com/activate | F15: AWS Activate Eligibility
B16: Cloud_Programs | C16: FAQ | D16: aws.amazon.com/activate | F16: AWS Activate FAQ
B17: Cloud_Programs | C17: Terms of Service | D17: cloud.google.com/startup | F17: Google for Startups Terms
... B29: Grants | C29: Guidelines | D29: sbir.gov | F29: SBIR/STTR Overview

Sheet ✈️ Pre-Flight Check
A1: CLOUD CREDIT PRE-FLIGHT VERIFICATION (Task 1C)
A2: Complete this table BEFORE any applications are submitted. Quote exact source language.
A4: Application | B4: Q1: LinkedIn Req? | C4: Q2: Website Req? | D4: Q3: Domain Email Req? | E4: Q4: Bootstrapped OK? | F4: Q5: Agency Exclusion? | G4: Q6: Credit Amount | H4: Source Docs | I4: Risk Flags | J4: Verdict
A5: AWS - SparkData Analytics
A6: AWS - Southwest Resume Services
A7: Google - SparkData Analytics
A8: Google - Southwest Resume Services
A9: Microsoft - SparkData Analytics
A10: Microsoft - Southwest Resume Services
A12: QUESTION GUIDANCE
A13: Q1 LinkedIn: | B13: Does program require LinkedIn company page? Answer: Yes/No. Source: [filename, page]
A14: Q2 Website: | B14: Does program require company website? Answer: Yes/No. If yes, note if domain email required.
A15: Q3 Domain Email: | B15: Does program require non-gmail email? Answer: Yes/No. Mark 'CEO INPUT NEEDED' if unknown.
A16: Q4 Bootstrapped: | B16: Are unfunded/bootstrapped companies eligible? Quote exact language from Terms/FAQ.
A17: Q5 Agency Exclusion: | B17: Does program exclude agencies/consultancies? Quote exact language. HIGHLIGHT for SRS apps.
A18: Q6 Credit Amount: | B18: What is starter tier credit amount? Any conditions/expiration? Quote source.
A19: Risk Flags: | B19: Summarize any concerns. Use: HIGH/MEDIUM/LOW/NONE
A20: Verdict: | B20: READY / BLOCKED - CEO INPUT / BLOCKED - EXCLUSION RISK / DO NOT APPLY

Sheet 📋 Program Facts
A1: PROGRAM FACT SHEETS (Task 1D)
A3: AWS ACTIVATE FOUNDERS
A4: Program Name:
A5: Program URL:
A6: Credit Amount (Starter):
A7: Credit Amount (Higher Tiers):
A8: Eligibility Requirements:
A9: Exclusions (exact language):
A10: Application URL:
A11: Required Documents:
A12: Approval Timeline:
A13: Credit Expiration:
... A42: Source Documents:

Sheet 📄 Proof Sheets
A1: PROGRAM PROOF SHEETS - ASSET STAGING (Task 2D)
A2: Stage all assets needed for applications. Mark CEO INPUT where you can't verify publicly.
A4: Field | B4: SparkData Analytics | C4: Southwest Resume Services | D4: Required For | E4: Notes
A5: Legal Entity Name | D5: All
A6: EIN | B6: [CEO INPUT] | C6: [CEO INPUT] | D6: All | E6: Do not guess
A7: Website URL | B7: [CEO INPUT] | C7: [CEO INPUT] | D7: All | E7: Verify if publicly known
A8: LinkedIn Company Page | D8: AWS, Google | E8: Verify exists or note DOES NOT EXIST
A9: Founder LinkedIn URL | B9: [CEO INPUT] | C9: [CEO INPUT] | D9: All
A10: Domain Email | B10: [CEO INPUT] | C10: [CEO INPUT] | D10: Google, Microsoft | E10: Must be @company.com, not gmail
A11: Date Founded | B11: [CEO INPUT] | C11: [CEO INPUT] | D11: All
A12: Physical Address | B12: [CEO INPUT] | C12: [CEO INPUT] | D12: All
A13: State of Incorporation | D13: Some
A14: Entity Type | D14: Some | E14: LLC, C-Corp, etc.
A15: Short Description (<100 chars) | B15: [CEO APPROVED TEXT] | C15: [CEO APPROVED TEXT] | D15: All | E15: I must approve this
A16: Long Description (<500 chars) | B16: [CEO APPROVED TEXT] | C16: [CEO APPROVED TEXT] | D16: Some | E16: I must approve this
A17: What are you building? | B17: [CEO APPROVED TEXT] | C17: [CEO APPROVED TEXT] | D17: Google | E17: I must approve this
A18: What will you use credits for? | B18: [CEO APPROVED TEXT] | C18: [CEO APPROVED TEXT] | D18: All | E18: I must approve this
A19: Current Stage | B19: Bootstrapped | C19: Bootstrapped | D19: All
A20: Funding Status | B20: $0 / Bootstrapped | C20: $0 / Bootstrapped | D20: All
A21: Employee Count | B21: [CEO INPUT] | C21: [CEO INPUT] | D21: Some

Sheet 🔑 CEO Inputs
A1: CEO DATA COLLECTION CHECKLIST (Task 2B)
A2: Every data point Ryan needs to provide. He fills Status column privately.
A4: Data Point | B4: Category | C4: Feeds Into | D4: Priority | E4: Status
A5: Net Self-Employment Income - SDA (Schedule C Line 31) | B5: Tax | C5: SEP-IRA Calculator | D5: HIGH
A6: Net Self-Employment Income - SRS (Schedule C Line 31) | B6: Tax | C6: SEP-IRA Calculator | D6: HIGH
A7: Total Health Insurance Premiums Paid 2024 | B7: Tax | C7: Health Ins Worksheet | D7: HIGH
A8: HSA Contributions Already Made 2024 | B8: Tax | C8: HSA Calculator | D8: MEDIUM
A9: HDHP Coverage Type (Self-only / Family) | B9: Tax | C9: HSA Calculator | D9: MEDIUM
A10: Home Office Square Footage | B10: Tax | C10: Home Office Calculator | D10: MEDIUM
A11: Total Home Square Footage | B11: Tax | C11: Home Office Calculator | D11: MEDIUM
A12: Total Home Expenses 2024 (rent/mortgage + utilities + insurance) | B12: Tax | C12: Home Office Calculator | D12: MEDIUM
A13: Estimated Business Miles Driven 2024 | B13: Tax | C13: Vehicle Calculator | D13: MEDIUM
A14: Eligible for Employer-Subsidized Health Coverage? (Y/N) | B14: Tax | C14: Health Ins Worksheet | D14: MEDIUM
A15: Taxable Income Estimate (for QBI threshold check) | B15: Tax | C15: QBI Estimator | D15: MEDIUM
A16: SparkData Analytics EIN | B16: Cloud Apps | C16: All Applications | D16: HIGH
... A32: Is SDA pursuing SBIR/STTR? | B32: Strategy | C32: AZ FAST Grant Eligibility | D32: LOW

Sheet 🧮 SEP-IRA Calc
A1: SEP-IRA CONTRIBUTION CALCULATOR
A2: Reference: IRS Publication 560
A4: INPUTS
A5: Net Self-Employment Income (Schedule C, Line 31): | C5: ← Enter amount here
A7: CALCULATIONS
A8: Step 1: Net Earnings × 0.9235 | B8: =B5*0.9235 -> 0 | C8: Adjustment for SE tax
A9: Step 2: SE Tax (Step 1 × 0.153) | B9: =B8*0.153 -> 0
A10: Step 3: SE Tax Deduction (Step 2 ÷ 2) | B10: =B9/2 -> 0
A11: Step 4: Net Earnings for SEP (Step 1 - Step 3) | B11: =B8-B10 -> 0
A12: Step 5: Contribution Rate | B12: 0.25 | C12: 25% max for SEP
A13: Step 6: Max Contribution (Step 4 × Step 5) | B13: =B11*B12 -> 0
A15: OUTPUT
A16: MAXIMUM SEP-IRA CONTRIBUTION: | B16: =MIN(B13,69000) -> 0 | C16: Capped at $69,000 for 2024
A18: Deadline: April 15, 2025 (or Oct 15, 2025 with extension)
A20: Source: IRS Publication 560, Chapter 5

Sheet 🧮 HSA Calc
A1: HSA CONTRIBUTION CALCULATOR
A2: Reference: IRS Publication 969
A4: HDHP ELIGIBILITY CHECK
A5: Do you have a High Deductible Health Plan (HDHP)? | C5: Enter YES or NO
A6: Coverage Type: | C6: Enter SELF or FAMILY
A7: Are you age 55 or older? | C7: Enter YES or NO
A9: 2024 HDHP REQUIREMENTS
A10: Self-Only: Min deductible $1,600 / Max OOP $8,050
A11: Family: Min deductible $3,200 / Max OOP $16,100
A13: 2024 CONTRIBUTION LIMITS
A14: Self-Only Coverage: | B14: $4,150
A15: Family Coverage: | B15: $8,300
A16: Catch-Up (age 55+): | B16: +$1,000
A18: CALCULATION
A19: HSA Contributions Already Made in 2024:
A20: Applicable Limit (based on coverage type): | C20: Enter $4,150 or $8,300 (+ $1,000 if 55+)
A22: OUTPUT
A23: REMAINING CONTRIBUTION ALLOWED: | B23: =B20-B19 -> 0
A25: Deadline: April 15, 2025

Sheet 🧮 Home Office Calc
A1: HOME OFFICE DEDUCTION CALCULATOR
A2: Reference: IRS Publication 587
A4: INPUTS
A5: Home Office Square Footage:
A6: Total Home Square Footage:
A7: Total Home Expenses 2024: | C7: (rent/mortgage interest + utilities + insurance)
A9: METHOD 1: SIMPLIFIED
A10: Rate: $5 per square foot
A11: Maximum: 300 sq ft ($1,500)
A12: Simplified Deduction: | B12: =MIN(B5*5,1500) -> 0
A14: METHOD 2: ACTUAL EXPENSES
A15: Business Use Percentage: | B15: =IF(B6>0,B5/B6,0) -> 0 | C15: (office sq ft ÷ total sq ft)
A16: Actual Expense Deduction: | B16: =B7*B15 -> 0
A18: OUTPUT
A19: RECOMMENDED METHOD: | B19: =IF(B12>B16,"SIMPLIFIED","ACTUAL") -> ACTUAL
A20: MAXIMUM DEDUCTION: | B20: =MAX(B12,B16) -> 0

Sheet 🧮 Vehicle Calc
A1: VEHICLE MILEAGE DEDUCTION CALCULATOR
A2: Reference: IRS Publication 463
A4: INPUTS
A5: Total Business Miles Driven 2024:
A7: FOR ACTUAL EXPENSE METHOD (optional):
A8: Total Vehicle Expenses (gas, insurance, repairs):
A9: Vehicle Depreciation:
A10: Total Miles Driven (all purposes):
A12: METHOD 1: STANDARD MILEAGE
A13: 2024 Rate: $0.67 per mile
A14: Standard Mileage Deduction: | B14: =B5*0.67 -> 0
A16: METHOD 2: ACTUAL EXPENSES
A17: Business Use Percentage: | B17: =IF(B10>0,B5/B10,0) -> 0
A18: Actual Expense Deduction: | B18: =(B8+B9)*B17 -> 0
A20: OUTPUT
A21: RECOMMENDED METHOD: | B21: =IF(B14>B18,"STANDARD","ACTUAL") -> ACTUAL
A22: MAXIMUM DEDUCTION: | B22: =MAX(B14,B18) -> 0
A24: NOTE: Must maintain contemporaneous mileage log for IRS compliance

Sheet 🧮 Health Ins Calc
A1: SELF-EMPLOYED HEALTH INSURANCE DEDUCTION
A4: INPUTS
A5: Total Health Insurance Premiums Paid 2024:
A6: Net Self-Employment Income (combined SDA + SRS):
A7: Were you eligible for employer-subsidized coverage? | C7: Enter YES or NO
A9: RULES
A10: • Deduction cannot exceed net self-employment income
A11: • Cannot claim if eligible for employer-subsidized plan (yours or spouse's)
A12: • This is an above-the-line deduction (Schedule 1, Line 17)
A14: OUTPUT
A15: ALLOWABLE DEDUCTION: | B15: =IF(B7="YES",0,MIN(B5,B6)) -> 0
A17: If $0: You answered YES to employer-subsidized coverage

Sheet 🧮 QBI Calc
A1: QBI DEDUCTION ESTIMATOR (Section 199A)
A2: Reference: Form 8995 Instructions
A4: INPUTS
A5: Taxable Income (before QBI deduction):
A6: Combined QBI from SDA + SRS:
A7: Filing Status: | C7: Enter SINGLE or MFJ
A9: 2024 THRESHOLDS
A10: Single: Full deduction if taxable income < $191,950
A11: MFJ: Full deduction if taxable income < $383,900
A12: Above thresholds: Phase-out calculations may apply
A14: CALCULATION
A15: Applicable Threshold: | B15: =IF(B7="SINGLE",191950,383900) -> 383900
A16: Below Threshold? | B16: =IF(B5<B15,"YES - Full 20%","CHECK PHASE-OUT") -> YES - Full 20%
A17: 20% of QBI: | B17: =B6*0.2 -> 0
A19: OUTPUT
A20: ESTIMATED QBI DEDUCTION: | B20: =IF(B5<B15,B17,"CONSULT CPA - PHASE-OUT") -> 0
A22: NOTE: QBI excludes SE tax deduction, SE health insurance, and retirement contributions
A23: This is calculated AFTER other deductions reduce your QBI

Sheet 🧮 Tax Summary
A1: TAX DEDUCTION SUMMARY DASHBOARD
A3: DEDUCTION CATEGORY | B3: AMOUNT | C3: SOURCE WORKSHEET
A4: SEP-IRA Contribution | B4: ='🧮 SEP-IRA Calc'!B16 -> 0 | C4: SEP-IRA Calc
A5: HSA Contribution | B5: ='🧮 HSA Calc'!B23 -> 0 | C5: HSA Calc
A6: Home Office Deduction | B6: ='🧮 Home Office Calc'!B20 -> 0 | C6: Home Office Calc
A7: Vehicle Mileage Deduction | B7: ='🧮 Vehicle Calc'!B22 -> 0 | C7: Vehicle Calc
A8: Self-Employed Health Insurance | B8: ='🧮 Health Ins Calc'!B15 -> 0 | C8: Health Ins Calc
A9: TOTAL DEDUCTIONS (before QBI): | B9: =SUM(B4:B8) -> 0
A11: QBI Deduction (calculated separately): | B11: ='🧮 QBI Calc'!B20 -> 0
A13: TARGET RANGE: $36,000 - $50,000
A15: KEY DEADLINES
A16: HSA Contribution: | B16: April 15, 2025
A17: SEP-IRA (with extension): | B17: October 15, 2025

Sheet 🏭 Vendor Whitelist
A1: DOMESTIC VENDOR WHITELIST (Task 2E)
A2: Under §174A, domestic R&D = immediate expensing. Foreign = 15-year amortization.
A4: Vendor | B4: HQ Location | C4: US-Based? | D4: Verification Source | E4: Bank Statement Descriptor
A5: OpenAI | E5: OPENAI
A6: Anthropic | E6: ANTHROPIC
A7: GitHub | E7: GITHUB
A8: Vercel | E8: VERCEL
A9: AWS | E9: AMAZON WEB SERVICES / AWS
A10: Google Cloud | E10: GOOGLE CLOUD / GCP
A11: Microsoft Azure | E11: MICROSOFT / AZURE
A12: Stripe | E12: STRIPE
A13: Twilio | E13: TWILIO
A14: MongoDB | E14: MONGODB
A15: Snowflake | E15: SNOWFLAKE
A16: Databricks | E16: DATABRICKS
... A29: DigitalOcean | E29: DIGITALOCEAN

Sheet 🔍 R&D Keywords
A1: R&D KEYWORD SEARCH LIST (Task 2E)
A2: Use these keywords to Ctrl+F bank/credit card statements for R&D expenses.
A4: CLOUD INFRASTRUCTURE
A5: API | B5: hosting | C5: compute | D5: server
A6: instance | B6: storage | C6: bandwidth | D6: CDN
A7: cluster | B7: container | C7: kubernetes | D7: docker
A8: lambda | B8: serverless | C8: EC2 | D8: S3
A10: AI / MACHINE LEARNING
A11: token | B11: inference | C11: embedding | D11: model
A12: training | B12: fine-tuning | C12: GPU | D12: CUDA
A13: neural | B13: LLM | C13: GPT | D13: Claude
A14: completion | B14: prompt | C14: vector | D14: RAG
A16: DEVELOPMENT TOOLS
A17: repository | B17: commit | C17: CI/CD | D17: deployment
A18: build | B18: test | C18: IDE | D18: compiler
A19: debugger | B19: version control | C19: git | D19: npm
A20: pip | B20: package
A22: DATA
A23: database | B23: query | C23: analytics | D23: pipeline
A24: ETL | B24: warehouse | C24: SQL | D24: NoSQL
A25: Postgres | B25: Redis | C25: Elasticsearch | D25: BigQuery
A27: SAAS / PRODUCTIVITY
A28: subscription | B28: workspace | C28: license | D28: seat
A29: pro plan | B29: team plan | C29: enterprise | D29: monthly
A30: annual

Sheet 💀 Grant Kill List
A1: GRANT KILL LIST (Task 2F)
A2: Systematically eliminate grants we don't qualify for. Most will be KILLED.
A4: AUTOMATIC DISQUALIFIERS (if ANY apply, mark KILLED)
A5: 1. Requires Non-Profit status (we are for-profit LLCs)
A6: 2. Requires >2 W-2 full-time employees (we don't have W-2 employees)
A7: 3. Sector mismatch (excludes tech, AI, software, or professional services)
A8: 4. Deadline has passed for current cycle
A9: 5. Award amount < $1,000 (not worth application effort)
A11: GRANT EVALUATION TABLE
A12: Grant Name | B12: Source Doc | C12: Award Amount | D12: Deadline | E12: Kill Criteria Met | F12: Employee Req | G12: Sector Req | H12: Notes | I12: VERDICT
A13: Arizona Innovation Challenge | C13: $50K-$250K | D13: Summer 2026
A14: AZ FAST Grant | C14: $3,000
A15: SBIR Phase I | C15: $50K-$275K | D15: Rolling
A19: VERDICT OPTIONS: KILLED / VIABLE / UNCERTAIN - CEO REVIEW

Sheet 🚨 Escalation Log
A1: ESCALATION LOG
A2: Log every escalation here. Include timestamp and resolution.
A4: Date/Time | B4: Task ID | C4: Trigger Type | D4: Description | E4: CEO Response | F4: Resolution
A5: Trigger Types: TIME_EXCEEDED / MISSING_INFO / AMBIGUOUS / STRATEGIC / ERROR_RISK

Sheet 📝 Daily Check-Ins
A1: DAILY CHECK-IN LOG
A3: Date | B3: COMPLETED | C3: BLOCKED | D3: TOMORROW | E3: QUESTIONS
A4: Mon Dec 23
A5: Tue Dec 24
A6: Thu Dec 26
A7: Fri Dec 27
